vulntrain/__init__.py
vulntrain/config/__init__.py
vulntrain/config/conf_sample.py
vulntrain/datasets/__init__.py
vulntrain/datasets/create_dataset.py
vulntrain/datasets/cwe-guesser-dataset.py
vulntrain/trainers/__init__.py
vulntrain/trainers/child_to_parent_mapping.json
vulntrain/trainers/classify_severity.py
vulntrain/trainers/classify_severity_cnvd.py
vulntrain/trainers/cwe_guesser_patches.py
vulntrain/trainers/cwe_hierarchy.json
vulntrain/trainers/deep_child_to_ancestor.json
vulntrain/trainers/generation_description.py
vulntrain/trainers/hierarchy.py
vulntrain/trainers/mapping_child_parent_cwe.py
vulntrain/trainers/parent_to_children_mapping.json
vulntrain/trainers/vulnerability.circl.lu.json
vulntrain/utils.py
vulntrain/validators/__init__.py
vulntrain/validators/benchmark-results.py
vulntrain/validators/benchmark_models.py
vulntrain/validators/evaluation.py
vulntrain/validators/severity.py
vulntrain/validators/summarize.py
vulntrain-2.1.0.dist-info/METADATA
vulntrain-2.1.0.dist-info/WHEEL
vulntrain-2.1.0.dist-info/entry_points.txt
vulntrain-2.1.0.dist-info/licenses/AUTHORS
vulntrain-2.1.0.dist-info/licenses/COPYING
vulntrain-2.1.0.dist-info/RECORD
