Metadata-Version: 2.4
Name: VulnTrain
Version: 2.1.0
Summary: Generate datasets amd models based on vulnerabilities data from Vulnerability-Lookup.
License-Expression: GPL-3.0-or-later
License-File: AUTHORS
License-File: COPYING
Author: Cédric Bonhomme
Author-email: cedric.bonhomme@circl.lu
Requires-Python: >=3.11,<4.0
Classifier: Development Status :: 5 - Production/Stable
Classifier: Environment :: Console
Classifier: Intended Audience :: Developers
Classifier: Intended Audience :: Science/Research
Classifier: License :: OSI Approved :: GNU General Public License v3 or later (GPLv3+)
Classifier: Operating System :: POSIX :: Linux
Classifier: Programming Language :: Python :: 3
Classifier: Programming Language :: Python :: 3.11
Classifier: Programming Language :: Python :: 3.12
Classifier: Programming Language :: Python :: 3.13
Classifier: Programming Language :: Python :: 3.14
Classifier: Programming Language :: Python :: 3.10
Classifier: Topic :: Security
Requires-Dist: codecarbon (>=2.8.3,<3.0.0)
Requires-Dist: cvss (>=3.4,<4.0)
Requires-Dist: datasets (>=3.5.0)
Requires-Dist: evaluate (>=0.4.3,<0.5.0)
Requires-Dist: markdown-it-py (>=3.0.0,<4.0.0)
Requires-Dist: nltk (>=3.9.1)
Requires-Dist: pandas (>=2.2.3)
Requires-Dist: scikit-learn (>=1.6.1,<2.0.0)
Requires-Dist: torch (>=2.7.0)
Requires-Dist: transformers[torch] (>=4.49.0,<5.0.0)
Requires-Dist: valkey (>=6.1.0)
Project-URL: Changelog, https://github.com/vulnerability-lookup/VulnTrain/blob/main/CHANGELOG.md
Project-URL: Homepage, https://github.com/vulnerability-lookup/VulnTrain
Project-URL: Repository, https://github.com/vulnerability-lookup/VulnTrain
